[
  {
    "client_msg_id": "b36825b4-ceb4-464e-b9b5-62fc1702c2ff",
    "type": "message",
    "text": "*DAILY STANDUP REMINDER*:timer_clock:\n*<!here>*  *<@U03TEPYRM2P>* \n Today's *standup*  will start in 10min! Join the meeting with this link below.\n:point_right: <http://meet.google.com/ysb-kjdn-hpp|meet.google.com/ysb-kjdn-hpp> (If you want to join now, we are listening to some good music)",
    "user": "U03V1AM5TFA",
    "ts": "1667375400.842719",
    "blocks": [
      {
        "type": "rich_text",
        "block_id": "U7/U",
        "elements": [
          {
            "type": "rich_text_section",
            "elements": [
              {
                "type": "text",
                "text": "DAILY STANDUP REMINDER",
                "style": {
                  "bold": true
                }
              },
              {
                "type": "emoji",
                "name": "timer_clock",
                "unicode": "23f2-fe0f"
              },
              {
                "type": "text",
                "text": "\n"
              },
              {
                "type": "broadcast",
                "range": "here",
                "style": {
                  "bold": true
                }
              },
              {
                "type": "text",
                "text": "  ",
                "style": {
                  "bold": true
                }
              },
              {
                "type": "user",
                "user_id": "U03TEPYRM2P",
                "style": {
                  "bold": true
                }
              },
              {
                "type": "text",
                "text": " ",
                "style": {
                  "bold": true
                }
              },
              {
                "type": "text",
                "text": "\n Today's"
              },
              {
                "type": "text",
                "text": " standup",
                "style": {
                  "bold": true
                }
              },
              {
                "type": "text",
                "text": "  will start in 10min! Join the meeting with this link below.\n"
              },
              {
                "type": "emoji",
                "name": "point_right",
                "unicode": "1f449"
              },
              {
                "type": "text",
                "text": " "
              },
              {
                "type": "link",
                "url": "http://meet.google.com/ysb-kjdn-hpp",
                "text": "meet.google.com/ysb-kjdn-hpp"
              },
              {
                "type": "text",
                "text": " (If you want to join now, we are listening to some good music)"
              }
            ]
          }
        ]
      }
    ],
    "team": "T03U4J8HMUG",
    "user_team": "T03U4J8HMUG",
    "source_team": "T03U4J8HMUG",
    "user_profile": {
      "avatar_hash": "102fdd0c183f",
      "image_72": "https://avatars.slack-edge.com/2022-08-19/3963732043714_102fdd0c183f8d6d4215_72.png",
      "first_name": "Vanessa",
      "real_name": "Vanessa Norman",
      "display_name": "Vanessa Norman",
      "team": "T03U4J8HMUG",
      "name": "Vanessa",
      "is_restricted": false,
      "is_ultra_restricted": false
    }
  },
  {
    "client_msg_id": "a9572c64-06cb-4b6e-88f5-7d8b7921a31f",
    "type": "message",
    "text": ":musical_note::musical_score::guitar:",
    "user": "U03V1AM5TFA",
    "ts": "1667375476.795119",
    "blocks": [
      {
        "type": "rich_text",
        "block_id": "EO=P1",
        "elements": [
          {
            "type": "rich_text_section",
            "elements": [
              {
                "type": "emoji",
                "name": "musical_note",
                "unicode": "1f3b5"
              },
              {
                "type": "emoji",
                "name": "musical_score",
                "unicode": "1f3bc"
              },
              {
                "type": "emoji",
                "name": "guitar",
                "unicode": "1f3b8"
              }
            ]
          }
        ]
      }
    ],
    "team": "T03U4J8HMUG",
    "user_team": "T03U4J8HMUG",
    "source_team": "T03U4J8HMUG",
    "user_profile": {
      "avatar_hash": "102fdd0c183f",
      "image_72": "https://avatars.slack-edge.com/2022-08-19/3963732043714_102fdd0c183f8d6d4215_72.png",
      "first_name": "Vanessa",
      "real_name": "Vanessa Norman",
      "display_name": "Vanessa Norman",
      "team": "T03U4J8HMUG",
      "name": "Vanessa",
      "is_restricted": false,
      "is_ultra_restricted": false
    }
  },
  {
    "client_msg_id": "2fe0e779-9a2c-4747-927b-0c0a2d315a48",
    "type": "message",
    "text": "We are starting Today's Standup, Please Join now",
    "user": "U03V1AM5TFA",
    "ts": "1667376027.189389",
    "blocks": [
      {
        "type": "rich_text",
        "block_id": "/Qiw",
        "elements": [
          {
            "type": "rich_text_section",
            "elements": [
              {
                "type": "text",
                "text": "We are starting Today's Standup, Please Join now"
              }
            ]
          }
        ]
      }
    ],
    "team": "T03U4J8HMUG",
    "user_team": "T03U4J8HMUG",
    "source_team": "T03U4J8HMUG",
    "user_profile": {
      "avatar_hash": "102fdd0c183f",
      "image_72": "https://avatars.slack-edge.com/2022-08-19/3963732043714_102fdd0c183f8d6d4215_72.png",
      "first_name": "Vanessa",
      "real_name": "Vanessa Norman",
      "display_name": "Vanessa Norman",
      "team": "T03U4J8HMUG",
      "name": "Vanessa",
      "is_restricted": false,
      "is_ultra_restricted": false
    }
  },
  {
    "client_msg_id": "01f5a7ae-27eb-481e-86fd-7982ffa1fc3a",
    "type": "message",
    "text": "*TUTORIAL REMINDER!!*:timer_clock:\n*<!here>* *<@U03TEPYRM2P>* *<@U03V8LHPDME>* \n*Please note that the next session is on in the next 10min*\n\u2022 *Session:* Image Segmentation with Yolo 7\n\u2022 *Time*:9:30 AM - 11:00 AM UTC (Login 5 min before the starting time)\n\u2022 *Platform:* Google meet. <http://meet.google.com/ysb-kjdn-hpp|meet.google.com/ysb-kjdn-hpp>\n",
    "user": "U03V1AM5TFA",
    "ts": "1667380801.131989",
    "blocks": [
      {
        "type": "rich_text",
        "block_id": "6yw7F",
        "elements": [
          {
            "type": "rich_text_section",
            "elements": [
              {
                "type": "text",
                "text": "TUTORIAL REMINDER!!",
                "style": {
                  "bold": true
                }
              },
              {
                "type": "emoji",
                "name": "timer_clock",
                "unicode": "23f2-fe0f",
                "style": {
                  "bold": true
                }
              },
              {
                "type": "text",
                "text": "\n"
              },
              {
                "type": "broadcast",
                "range": "here",
                "style": {
                  "bold": true
                }
              },
              {
                "type": "text",
                "text": " ",
                "style": {
                  "bold": true
                }
              },
              {
                "type": "user",
                "user_id": "U03TEPYRM2P",
                "style": {
                  "bold": true
                }
              },
              {
                "type": "text",
                "text": " ",
                "style": {
                  "bold": true
                }
              },
              {
                "type": "user",
                "user_id": "U03V8LHPDME",
                "style": {
                  "bold": true
                }
              },
              {
                "type": "text",
                "text": " ",
                "style": {
                  "bold": true
                }
              },
              {
                "type": "text",
                "text": "\n"
              },
              {
                "type": "text",
                "text": "Please note that the next session is on in the next 10min",
                "style": {
                  "bold": true
                }
              },
              {
                "type": "text",
                "text": "\n"
              }
            ]
          },
          {
            "type": "rich_text_list",
            "elements": [
              {
                "type": "rich_text_section",
                "elements": [
                  {
                    "type": "text",
                    "text": "Session: ",
                    "style": {
                      "bold": true
                    }
                  },
                  {
                    "type": "text",
                    "text": "Image Segmentation with Yolo 7"
                  }
                ]
              },
              {
                "type": "rich_text_section",
                "elements": [
                  {
                    "type": "text",
                    "text": "Time",
                    "style": {
                      "bold": true
                    }
                  },
                  {
                    "type": "text",
                    "text": ":9:30 AM - 11:00 AM UTC (Login 5 min before the starting time)"
                  }
                ]
              },
              {
                "type": "rich_text_section",
                "elements": [
                  {
                    "type": "text",
                    "text": "Platform: ",
                    "style": {
                      "bold": true
                    }
                  },
                  {
                    "type": "text",
                    "text": "Google meet. "
                  },
                  {
                    "type": "link",
                    "url": "http://meet.google.com/ysb-kjdn-hpp",
                    "text": "meet.google.com/ysb-kjdn-hpp"
                  }
                ]
              }
            ],
            "style": "bullet",
            "indent": 0,
            "border": 0
          },
          {
            "type": "rich_text_section",
            "elements": []
          }
        ]
      }
    ],
    "team": "T03U4J8HMUG",
    "user_team": "T03U4J8HMUG",
    "source_team": "T03U4J8HMUG",
    "user_profile": {
      "avatar_hash": "102fdd0c183f",
      "image_72": "https://avatars.slack-edge.com/2022-08-19/3963732043714_102fdd0c183f8d6d4215_72.png",
      "first_name": "Vanessa",
      "real_name": "Vanessa Norman",
      "display_name": "Vanessa Norman",
      "team": "T03U4J8HMUG",
      "name": "Vanessa",
      "is_restricted": false,
      "is_ultra_restricted": false
    }
  },
  {
    "client_msg_id": "b99fa427-272c-4e84-9e03-504dc7e8b190",
    "type": "message",
    "text": "*FEMALE-ONLY SESSION REMINDER*\n*: <!here>: <@U03UP7V9Q57>* \nPlease note that _*Female  session*_ is on in the next 10min\n*Time: from 11:00 AM -12:00 PM UTC*\n\n&gt; *NB: The session is only for Female*",
    "user": "U03V1AM5TFA",
    "ts": "1667386200.887549",
    "blocks": [
      {
        "type": "rich_text",
        "block_id": "oNl",
        "elements": [
          {
            "type": "rich_text_section",
            "elements": [
              {
                "type": "text",
                "text": "FEMALE-ONLY SESSION REMINDER",
                "style": {
                  "bold": true
                }
              },
              {
                "type": "text",
                "text": "\n"
              },
              {
                "type": "text",
                "text": ": ",
                "style": {
                  "bold": true
                }
              },
              {
                "type": "broadcast",
                "range": "here",
                "style": {
                  "bold": true
                }
              },
              {
                "type": "text",
                "text": ": ",
                "style": {
                  "bold": true
                }
              },
              {
                "type": "user",
                "user_id": "U03UP7V9Q57",
                "style": {
                  "bold": true
                }
              },
              {
                "type": "text",
                "text": " ",
                "style": {
                  "bold": true
                }
              },
              {
                "type": "text",
                "text": "\nPlease note that "
              },
              {
                "type": "text",
                "text": "Female  session",
                "style": {
                  "bold": true,
                  "italic": true
                }
              },
              {
                "type": "text",
                "text": " ",
                "style": {
                  "bold": true
                }
              },
              {
                "type": "text",
                "text": "is on in the next 10min\n"
              },
              {
                "type": "text",
                "text": "Time: from 11:00 AM -12:00 PM UTC",
                "style": {
                  "bold": true
                }
              },
              {
                "type": "text",
                "text": "\n\n"
              }
            ]
          },
          {
            "type": "rich_text_quote",
            "elements": [
              {
                "type": "text",
                "text": "NB: The session is only for Female",
                "style": {
                  "bold": true
                }
              }
            ]
          }
        ]
      }
    ],
    "team": "T03U4J8HMUG",
    "user_team": "T03U4J8HMUG",
    "source_team": "T03U4J8HMUG",
    "user_profile": {
      "avatar_hash": "102fdd0c183f",
      "image_72": "https://avatars.slack-edge.com/2022-08-19/3963732043714_102fdd0c183f8d6d4215_72.png",
      "first_name": "Vanessa",
      "real_name": "Vanessa Norman",
      "display_name": "Vanessa Norman",
      "team": "T03U4J8HMUG",
      "name": "Vanessa",
      "is_restricted": false,
      "is_ultra_restricted": false
    }
  },
  {
    "client_msg_id": "1454367c-cc5f-4aa1-839b-ae6a9e0b1c47",
    "type": "message",
    "text": "*Independent challenge work Reminder!! <!here>*\n*Please note that Independent Challenge Work is  in the next 10min*\n\u2022 *Session:* Independent challenge work (You will be working independently on today's challenge)\n\u2022 *Time*: From 2:00 PM - 8:00 PM UTC.\n",
    "user": "U03V1AM5TFA",
    "ts": "1667397001.220779",
    "blocks": [
      {
        "type": "rich_text",
        "block_id": "MAJkU",
        "elements": [
          {
            "type": "rich_text_section",
            "elements": [
              {
                "type": "text",
                "text": "Independent challenge work Reminder!! ",
                "style": {
                  "bold": true
                }
              },
              {
                "type": "broadcast",
                "range": "here",
                "style": {
                  "bold": true
                }
              },
              {
                "type": "text",
                "text": "\n"
              },
              {
                "type": "text",
                "text": "Please note that Independent Challenge Work is  in the next 10min",
                "style": {
                  "bold": true
                }
              },
              {
                "type": "text",
                "text": "\n"
              }
            ]
          },
          {
            "type": "rich_text_list",
            "elements": [
              {
                "type": "rich_text_section",
                "elements": [
                  {
                    "type": "text",
                    "text": "Session: ",
                    "style": {
                      "bold": true
                    }
                  },
                  {
                    "type": "text",
                    "text": "Independent challenge work (You will be working independently on today's challenge)"
                  }
                ]
              },
              {
                "type": "rich_text_section",
                "elements": [
                  {
                    "type": "text",
                    "text": "Time",
                    "style": {
                      "bold": true
                    }
                  },
                  {
                    "type": "text",
                    "text": ": From 2:00 PM - 8:00 PM UTC."
                  }
                ]
              }
            ],
            "style": "bullet",
            "indent": 0,
            "border": 0
          },
          {
            "type": "rich_text_section",
            "elements": []
          }
        ]
      }
    ],
    "team": "T03U4J8HMUG",
    "user_team": "T03U4J8HMUG",
    "source_team": "T03U4J8HMUG",
    "user_profile": {
      "avatar_hash": "102fdd0c183f",
      "image_72": "https://avatars.slack-edge.com/2022-08-19/3963732043714_102fdd0c183f8d6d4215_72.png",
      "first_name": "Vanessa",
      "real_name": "Vanessa Norman",
      "display_name": "Vanessa Norman",
      "team": "T03U4J8HMUG",
      "name": "Vanessa",
      "is_restricted": false,
      "is_ultra_restricted": false
    }
  },
  {
    "client_msg_id": "6c90c10f-69c7-4839-ba91-86e21a5d1cfc",
    "type": "message",
    "text": "\u2022 Reminder!:timer_clock::timer_clock: *<!here>*\n*Please note that the deadline to submit Weekly challenge(*week 11 Interim Submission (technical)) *is in 30Min.*\n*Kindly don't miss the deadline.*",
    "user": "U03V1AM5TFA",
    "ts": "1667417400.532709",
    "blocks": [
      {
        "type": "rich_text",
        "block_id": "2fBlf",
        "elements": [
          {
            "type": "rich_text_list",
            "elements": [
              {
                "type": "rich_text_section",
                "elements": [
                  {
                    "type": "text",
                    "text": "Reminder!"
                  },
                  {
                    "type": "emoji",
                    "name": "timer_clock",
                    "unicode": "23f2-fe0f",
                    "style": {
                      "bold": true
                    }
                  },
                  {
                    "type": "emoji",
                    "name": "timer_clock",
                    "unicode": "23f2-fe0f",
                    "style": {
                      "bold": true
                    }
                  },
                  {
                    "type": "text",
                    "text": " ",
                    "style": {
                      "bold": true
                    }
                  },
                  {
                    "type": "broadcast",
                    "range": "here",
                    "style": {
                      "bold": true
                    }
                  }
                ]
              }
            ],
            "style": "bullet",
            "indent": 0,
            "border": 0
          },
          {
            "type": "rich_text_section",
            "elements": [
              {
                "type": "text",
                "text": "Please note that the deadline to submit Weekly challenge(",
                "style": {
                  "bold": true
                }
              },
              {
                "type": "text",
                "text": "week 11 Interim Submission (technical))"
              },
              {
                "type": "text",
                "text": " is in 30Min.",
                "style": {
                  "bold": true
                }
              },
              {
                "type": "text",
                "text": "\n"
              },
              {
                "type": "text",
                "text": "Kindly don't miss the deadline.",
                "style": {
                  "bold": true
                }
              }
            ]
          }
        ]
      }
    ],
    "team": "T03U4J8HMUG",
    "user_team": "T03U4J8HMUG",
    "source_team": "T03U4J8HMUG",
    "user_profile": {
      "avatar_hash": "102fdd0c183f",
      "image_72": "https://avatars.slack-edge.com/2022-08-19/3963732043714_102fdd0c183f8d6d4215_72.png",
      "first_name": "Vanessa",
      "real_name": "Vanessa Norman",
      "display_name": "Vanessa Norman",
      "team": "T03U4J8HMUG",
      "name": "Vanessa",
      "is_restricted": false,
      "is_ultra_restricted": false
    }
  }
]