[
  {
    "client_msg_id": "50247366-5858-4682-9453-4e3a2bd7181e",
    "type": "message",
    "text": "If you're still struggling to piece together D.E concepts, this video could help. <https://www.youtube.com/watch?v=qWru-b6m030>",
    "user": "U03V785NLSU",
    "ts": "1667991819.359389",
    "blocks": [
      {
        "type": "rich_text",
        "block_id": "maLw",
        "elements": [
          {
            "type": "rich_text_section",
            "elements": [
              {
                "type": "text",
                "text": "If you're still struggling to piece together D.E concepts, this video could help. "
              },
              {
                "type": "link",
                "url": "https://www.youtube.com/watch?v=qWru-b6m030"
              }
            ]
          }
        ]
      }
    ],
    "team": "T03U4J8HMUG",
    "user_team": "T03U4J8HMUG",
    "source_team": "T03U4J8HMUG",
    "user_profile": {
      "avatar_hash": "48d5c88821e9",
      "image_72": "https://avatars.slack-edge.com/2022-08-21/3993277785968_48d5c88821e922581e17_72.jpg",
      "first_name": "Ashley",
      "real_name": "Ashley Hamilton",
      "display_name": "Ashley Hamilton",
      "team": "T03U4J8HMUG",
      "name": "Ashley",
      "is_restricted": false,
      "is_ultra_restricted": false
    },
    "attachments": [
      {
        "from_url": "https://www.youtube.com/watch?v=qWru-b6m030",
        "thumb_url": "https://i.ytimg.com/vi/qWru-b6m030/hqdefault.jpg",
        "thumb_width": 480,
        "thumb_height": 360,
        "video_html": "<iframe width=\"400\" height=\"225\" src=\"https://www.youtube.com/embed/qWru-b6m030?feature=oembed&autoplay=1&iv_load_policy=3\" frameborder=\"0\" allow=\"accelerometer; autoplay; clipboard-write; encrypted-media; gyroscope; picture-in-picture\" allowfullscreen title=\"How Data Engineering Works\"></iframe>",
        "video_html_width": 400,
        "video_html_height": 225,
        "service_icon": "https://a.slack-edge.com/80588/img/unfurl_icons/youtube.png",
        "id": 1,
        "original_url": "https://www.youtube.com/watch?v=qWru-b6m030",
        "fallback": "YouTube Video: How Data Engineering Works",
        "title": "How Data Engineering Works",
        "title_link": "https://www.youtube.com/watch?v=qWru-b6m030",
        "author_name": "AltexSoft",
        "author_link": "https://www.youtube.com/c/AltexSoft",
        "service_name": "YouTube",
        "service_url": "https://www.youtube.com/"
      }
    ],
    "reactions": [
      {
        "name": "raised_hands",
        "users": [
          "U03UVHCV6KB"
        ],
        "count": 1
      },
      {
        "name": "white_check_mark",
        "users": [
          "U03UVHCV6KB"
        ],
        "count": 1
      }
    ]
  },
  {
    "client_msg_id": "694a6590-9897-4e4d-bf41-3a92d68d5f19",
    "type": "message",
    "text": "<https://youtu.be/P1u8x3ycqvg?list=PL3MmuxUbc_hJed7dXYoJw8DoCuVHhGEQb>",
    "user": "U03UG32J3PC",
    "ts": "1668012283.405179",
    "blocks": [
      {
        "type": "rich_text",
        "block_id": "ZsJ",
        "elements": [
          {
            "type": "rich_text_section",
            "elements": [
              {
                "type": "link",
                "url": "https://youtu.be/P1u8x3ycqvg?list=PL3MmuxUbc_hJed7dXYoJw8DoCuVHhGEQb"
              }
            ]
          }
        ]
      }
    ],
    "team": "T03U4J8HMUG",
    "user_team": "T03U4J8HMUG",
    "source_team": "T03U4J8HMUG",
    "user_profile": {
      "avatar_hash": "g9e7487b036e",
      "image_72": "https://secure.gravatar.com/avatar/9e7487b036ed726d016a0c5d8189773c.jpg?s=72&d=https%3A%2F%2Fa.slack-edge.com%2Fdf10d%2Fimg%2Favatars%2Fava_0005-72.png",
      "first_name": "April",
      "real_name": "April Lucas",
      "display_name": "April Lucas",
      "team": "T03U4J8HMUG",
      "name": "April",
      "is_restricted": false,
      "is_ultra_restricted": false
    },
    "attachments": [
      {
        "from_url": "https://youtu.be/P1u8x3ycqvg",
        "thumb_url": "https://i.ytimg.com/vi/P1u8x3ycqvg/hqdefault.jpg",
        "thumb_width": 480,
        "thumb_height": 360,
        "video_html": "<iframe width=\"400\" height=\"225\" src=\"https://www.youtube.com/embed/P1u8x3ycqvg?feature=oembed&autoplay=1&iv_load_policy=3\" frameborder=\"0\" allow=\"accelerometer; autoplay; clipboard-write; encrypted-media; gyroscope; picture-in-picture\" allowfullscreen title=\"DE Zoomcamp 6.1.1 - Kafka introduction\"></iframe>",
        "video_html_width": 400,
        "video_html_height": 225,
        "service_icon": "https://a.slack-edge.com/80588/img/unfurl_icons/youtube.png",
        "id": 1,
        "original_url": "https://youtu.be/P1u8x3ycqvg?list=PL3MmuxUbc_hJed7dXYoJw8DoCuVHhGEQb",
        "fallback": "YouTube Video: DE Zoomcamp 6.1.1 - Kafka introduction",
        "title": "DE Zoomcamp 6.1.1 - Kafka introduction",
        "title_link": "https://youtu.be/P1u8x3ycqvg",
        "author_name": "DataTalksClub \u2b1b",
        "author_link": "https://www.youtube.com/c/DataTalksClub",
        "service_name": "YouTube",
        "service_url": "https://www.youtube.com/"
      }
    ]
  },
  {
    "client_msg_id": "b3fdd8ba-531b-41a0-b7ac-b47880e97775",
    "type": "message",
    "text": "<https://developer.confluent.io/what-is-apache-kafka/>",
    "user": "U03UG32J3PC",
    "ts": "1668014128.420309",
    "blocks": [
      {
        "type": "rich_text",
        "block_id": "40u8a",
        "elements": [
          {
            "type": "rich_text_section",
            "elements": [
              {
                "type": "link",
                "url": "https://developer.confluent.io/what-is-apache-kafka/"
              }
            ]
          }
        ]
      }
    ],
    "team": "T03U4J8HMUG",
    "user_team": "T03U4J8HMUG",
    "source_team": "T03U4J8HMUG",
    "user_profile": {
      "avatar_hash": "g9e7487b036e",
      "image_72": "https://secure.gravatar.com/avatar/9e7487b036ed726d016a0c5d8189773c.jpg?s=72&d=https%3A%2F%2Fa.slack-edge.com%2Fdf10d%2Fimg%2Favatars%2Fava_0005-72.png",
      "first_name": "April",
      "real_name": "April Lucas",
      "display_name": "April Lucas",
      "team": "T03U4J8HMUG",
      "name": "April",
      "is_restricted": false,
      "is_ultra_restricted": false
    },
    "attachments": [
      {
        "from_url": "https://developer.confluent.io/what-is-apache-kafka/",
        "thumb_url": "https://developer.confluent.io/images/developer-thumbnail.jpg",
        "thumb_width": 500,
        "thumb_height": 500,
        "service_icon": "https://developer.confluent.io/favicon.ico",
        "id": 1,
        "original_url": "https://developer.confluent.io/what-is-apache-kafka/",
        "fallback": "Confluent: What is Kafka, and How Does it Work? A Tutorial for Beginners",
        "text": "Apache Kafka is a data streaming system used for real-time data pipelines, data integration, and event-driven systems. Learn how Kafka works with examples and use cases.",
        "title": "What is Kafka, and How Does it Work? A Tutorial for Beginners",
        "title_link": "https://developer.confluent.io/what-is-apache-kafka/",
        "service_name": "Confluent"
      }
    ]
  },
  {
    "client_msg_id": "74d511c7-e3bb-442e-ab24-c16342dfd0ca",
    "type": "message",
    "text": "<https://medium.com/analytics-vidhya/making-sense-of-stream-data-b74c1252a8f5>",
    "user": "U03UG32J3PC",
    "ts": "1668014137.117299",
    "blocks": [
      {
        "type": "rich_text",
        "block_id": "F=GZ",
        "elements": [
          {
            "type": "rich_text_section",
            "elements": [
              {
                "type": "link",
                "url": "https://medium.com/analytics-vidhya/making-sense-of-stream-data-b74c1252a8f5"
              }
            ]
          }
        ]
      }
    ],
    "team": "T03U4J8HMUG",
    "user_team": "T03U4J8HMUG",
    "source_team": "T03U4J8HMUG",
    "user_profile": {
      "avatar_hash": "g9e7487b036e",
      "image_72": "https://secure.gravatar.com/avatar/9e7487b036ed726d016a0c5d8189773c.jpg?s=72&d=https%3A%2F%2Fa.slack-edge.com%2Fdf10d%2Fimg%2Favatars%2Fava_0005-72.png",
      "first_name": "April",
      "real_name": "April Lucas",
      "display_name": "April Lucas",
      "team": "T03U4J8HMUG",
      "name": "April",
      "is_restricted": false,
      "is_ultra_restricted": false
    },
    "attachments": [
      {
        "from_url": "https://medium.com/analytics-vidhya/making-sense-of-stream-data-b74c1252a8f5",
        "ts": 1575274931,
        "image_url": "https://miro.medium.com/max/1200/1*twyCFLpb2mkWOZR4IUoBKA.jpeg",
        "image_width": 375,
        "image_height": 250,
        "image_bytes": 113866,
        "service_icon": "https://miro.medium.com/fit/c/152/152/1*sHhtYhaCe2Uc3IU0IgKwIQ.png",
        "id": 1,
        "original_url": "https://medium.com/analytics-vidhya/making-sense-of-stream-data-b74c1252a8f5",
        "fallback": "Medium: Making sense of Stream Data",
        "text": "Have you ever wondered while working with Kafka and Kafka streams, how you could showcase your project to stakeholders, highlight\u2026",
        "title": "Making sense of Stream Data",
        "title_link": "https://medium.com/analytics-vidhya/making-sense-of-stream-data-b74c1252a8f5",
        "service_name": "Medium",
        "fields": [
          {
            "value": "6 min read",
            "title": "Reading time",
            "short": true
          }
        ]
      }
    ]
  },
  {
    "client_msg_id": "1bbba61e-dd80-46bf-9ecd-0184ee8b632b",
    "type": "message",
    "text": "<https://www.youtube.com/watch?v=6kEGUCrBEU0>",
    "user": "U03UFV7HFNF",
    "ts": "1668020505.472119",
    "blocks": [
      {
        "type": "rich_text",
        "block_id": "rTM1",
        "elements": [
          {
            "type": "rich_text_section",
            "elements": [
              {
                "type": "link",
                "url": "https://www.youtube.com/watch?v=6kEGUCrBEU0"
              }
            ]
          }
        ]
      }
    ],
    "team": "T03U4J8HMUG",
    "user_team": "T03U4J8HMUG",
    "source_team": "T03U4J8HMUG",
    "user_profile": {
      "avatar_hash": "3166d51d23f1",
      "image_72": "https://avatars.slack-edge.com/2022-08-20/3991799522480_3166d51d23f1da2374e9_72.jpg",
      "first_name": "Miguel",
      "real_name": "Miguel Herring",
      "display_name": "Miguel Herring",
      "team": "T03U4J8HMUG",
      "name": "Miguel",
      "is_restricted": false,
      "is_ultra_restricted": false
    },
    "attachments": [
      {
        "from_url": "https://www.youtube.com/watch?v=6kEGUCrBEU0",
        "thumb_url": "https://i.ytimg.com/vi/6kEGUCrBEU0/hqdefault.jpg",
        "thumb_width": 480,
        "thumb_height": 360,
        "video_html": "<iframe width=\"400\" height=\"225\" src=\"https://www.youtube.com/embed/6kEGUCrBEU0?feature=oembed&autoplay=1&iv_load_policy=3\" frameborder=\"0\" allow=\"accelerometer; autoplay; clipboard-write; encrypted-media; gyroscope; picture-in-picture\" allowfullscreen title=\"Data Pipelines Explained\"></iframe>",
        "video_html_width": 400,
        "video_html_height": 225,
        "service_icon": "https://a.slack-edge.com/80588/img/unfurl_icons/youtube.png",
        "id": 1,
        "original_url": "https://www.youtube.com/watch?v=6kEGUCrBEU0",
        "fallback": "YouTube Video: Data Pipelines Explained",
        "title": "Data Pipelines Explained",
        "title_link": "https://www.youtube.com/watch?v=6kEGUCrBEU0",
        "author_name": "IBM Technology",
        "author_link": "https://www.youtube.com/c/IBMTechnology",
        "service_name": "YouTube",
        "service_url": "https://www.youtube.com/"
      }
    ]
  }
]