[
  {
    "client_msg_id": "02946189-130b-40f6-b16d-8d9454453ef2",
    "type": "message",
    "text": "Morning <!channel>\nWeek 6 careers exercise is a redo of week 3 - Developing curiosity.\nThere will be a \"how to ask question\" session on Wednesday 9 am UTC",
    "user": "U03TT5KEYCF",
    "ts": "1664182273.896489",
    "blocks": [
      {
        "type": "rich_text",
        "block_id": "qU9Xx",
        "elements": [
          {
            "type": "rich_text_section",
            "elements": [
              {
                "type": "text",
                "text": "Morning "
              },
              {
                "type": "broadcast",
                "range": "channel"
              },
              {
                "type": "text",
                "text": "\nWeek 6 careers exercise is a redo of week 3 - Developing curiosity.\nThere will be a \"how to ask question\" session on Wednesday 9 am UTC"
              }
            ]
          }
        ]
      }
    ],
    "team": "T03U4J8HMUG",
    "user_team": "T03U4J8HMUG",
    "source_team": "T03U4J8HMUG",
    "user_profile": {
      "avatar_hash": "aae36184306b",
      "image_72": "https://avatars.slack-edge.com/2022-08-18/3945210198087_aae36184306bb9e0b018_72.jpg",
      "first_name": "Luis",
      "real_name": "Luis Ingram",
      "display_name": "Luis Ingram",
      "team": "T03U4J8HMUG",
      "name": "Luis",
      "is_restricted": false,
      "is_ultra_restricted": false
    }
  },
  {
    "client_msg_id": "5792332f-184f-4dc2-8831-960559b4ee29",
    "type": "message",
    "text": "<@U03UUR571A5> <@U03UFV7HFNF> <@U03U1HAG9TR> <@U03UD4FEDHB> Please kindly share your CV with me in preparation for tomorrow's mock interview.\nThanks !",
    "user": "U03TT5KEYCF",
    "ts": "1664182402.657149",
    "blocks": [
      {
        "type": "rich_text",
        "block_id": "8dmlC",
        "elements": [
          {
            "type": "rich_text_section",
            "elements": [
              {
                "type": "user",
                "user_id": "U03UUR571A5"
              },
              {
                "type": "text",
                "text": " "
              },
              {
                "type": "user",
                "user_id": "U03UFV7HFNF"
              },
              {
                "type": "text",
                "text": " "
              },
              {
                "type": "user",
                "user_id": "U03U1HAG9TR"
              },
              {
                "type": "text",
                "text": " "
              },
              {
                "type": "user",
                "user_id": "U03UD4FEDHB"
              },
              {
                "type": "text",
                "text": " Please kindly share your CV with me in preparation for tomorrow's mock interview.\nThanks !"
              }
            ]
          }
        ]
      }
    ],
    "team": "T03U4J8HMUG",
    "user_team": "T03U4J8HMUG",
    "source_team": "T03U4J8HMUG",
    "user_profile": {
      "avatar_hash": "aae36184306b",
      "image_72": "https://avatars.slack-edge.com/2022-08-18/3945210198087_aae36184306bb9e0b018_72.jpg",
      "first_name": "Luis",
      "real_name": "Luis Ingram",
      "display_name": "Luis Ingram",
      "team": "T03U4J8HMUG",
      "name": "Luis",
      "is_restricted": false,
      "is_ultra_restricted": false
    },
    "reactions": [
      {
        "name": "raised_hands",
        "users": [
          "U03UFV7HFNF"
        ],
        "count": 1
      }
    ]
  }
]